[
  {
    "sku": "DEMO001",
    "name": "Exobrace",
    "description": "No more scoliosis",
    "image": "https://www.medstarhealth.org/-/media/project/mho/medstar/services/spine_1200x628.jpg",
    "amount": 10000,
    "currency": "USD"
  },
  {
    "sku": "DEMO002",
    "name": "Exobrace + 2 Months of Visits",
    "description": "You should probably buy this one",
    "image": "https://images.unsplash.com/photo-1454329001438-1752daa90420?auto=format&fit=crop&w=600&h=600&q=80",
    "amount": 15000,
    "currency": "USD"
  }
]
